fpg_cli/__init__.py
fpg_cli/main.py
fpg_cli-0.2.0.dist-info/licenses/LICENSE
fpg_cli-0.2.0.dist-info/METADATA
fpg_cli-0.2.0.dist-info/WHEEL
fpg_cli-0.2.0.dist-info/entry_points.txt
fpg_cli-0.2.0.dist-info/top_level.txt
fpg_cli-0.2.0.dist-info/RECORD
