Metadata-Version: 2.4
Name: fpg-cli
Version: 0.2.0
Summary: Add your description here
Requires-Python: >=3.11
License-File: LICENSE
Requires-Dist: requests>=2.32.5
Requires-Dist: typer>=0.19.2
Dynamic: license-file
